kubecargoload.py
kube_cargo_load-1.2.dist-info/LICENSE
kube_cargo_load-1.2.dist-info/METADATA
kube_cargo_load-1.2.dist-info/WHEEL
kube_cargo_load-1.2.dist-info/entry_points.txt
kube_cargo_load-1.2.dist-info/top_level.txt
kube_cargo_load-1.2.dist-info/RECORD
