Metadata-Version: 2.1
Name: kube-cargo-load
Version: 1.2
Summary: Kubernetes POD memory limits and usage overview.
Home-page: https://github.com/eht16/kube-cargo-load
Author: Enrico Tröger
Author-email: enrico.troeger@uvena.de
License: Apache License 2.0
Project-URL: Source code, https://github.com/eht16/kube-cargo-load/
Keywords: kubernetes pod memory usage
Platform: UNKNOWN
Classifier: Development Status :: 5 - Production/Stable
Classifier: Intended Audience :: Developers
Classifier: Intended Audience :: System Administrators
Classifier: License :: OSI Approved :: Apache Software License
Classifier: Operating System :: OS Independent
Classifier: Programming Language :: Python
Classifier: Programming Language :: Python :: 3
